MANIFEST.in
README.txt
setup.py
examples/sample.conf
examples/sistagen.conf
examples/test.conf
rrd/__init__.py
rrd/graph.py
sistagen/__init__.py
sistagen/arguments.py
sistagen/cfgparser.py
sistagen/declaration.py
sistagen/help.py
sistagen/sistagen.py
sistagen/version.py
sistagen.egg-info/PKG-INFO
sistagen.egg-info/SOURCES.txt
sistagen.egg-info/dependency_links.txt
sistagen.egg-info/entry_points.txt
sistagen.egg-info/requires.txt
sistagen.egg-info/top_level.txt
templates/colors.conf
templates/templates.conf