Metadata-Version: 1.1
Name: sistagen
Version: 1.0.47
Summary: Simple Stat Generator
Home-page: https://launchpad.net/sistagen
Author: Sławek Lis
Author-email: lis.slawek@gmail.com
License: BSD
Platform: UNKNOWN
Classifier: Development Status :: 4 - Beta
Classifier: Environment :: Console
Classifier: License :: OSI Approved :: BSD License
Classifier: Operating System :: OS Independent
Classifier: Programming Language :: Python :: 2.6
Classifier: Programming Language :: Python :: 2.7
Classifier: Programming Language :: Python :: 3.1
Classifier: Programming Language :: Python :: 3.2
Classifier: Programming Language :: Python :: 3.3
Classifier: Topic :: System :: Monitoring
Classifier: Topic :: Utilities
